setup.cfg
setup.py
testprodgekt/__init__.py
testprodgekt.egg-info/PKG-INFO
testprodgekt.egg-info/SOURCES.txt
testprodgekt.egg-info/dependency_links.txt
testprodgekt.egg-info/requires.txt
testprodgekt.egg-info/top_level.txt