Metadata-Version: 2.2
Name: testprodgekt
Version: 1.1
Author: DavidYdin
Author-email: David.2280@yandex.ru
Requires-Python: >=3.11
Requires-Dist: keyboard
Dynamic: author
Dynamic: author-email
Dynamic: requires-dist
Dynamic: requires-python
